okgtreg
