Metadata-Version: 1.1
Name: okgtreg
Version: 0.14
Summary: Implementation of Optimal Kernel Group Optimization for regression
Home-page: http://www.stat.purdue.edu/~panc
Author: Pan Chao
Author-email: panc@purdue.edu
License: UNKNOWN
Keywords: OKGT regression exploratory data analysis
Platform: UNKNOWN
Classifier: Development Status :: 3 - Alpha
Classifier: Programming Language :: Python :: 2.7
